claude_cml_toolkit/__init__.py
claude_cml_toolkit/server.py
claude_cml_toolkit/client/__init__.py
claude_cml_toolkit/client/cml_client.py
claude_cml_toolkit/handlers/__init__.py
claude_cml_toolkit/handlers/configuration.py
claude_cml_toolkit/handlers/console.py
claude_cml_toolkit/handlers/lab_management.py
claude_cml_toolkit/handlers/topology.py
claude_cml_toolkit/utils/__init__.py
claude_cml_toolkit/utils/helpers.py
claude_cml_toolkit-2.0.8.dist-info/METADATA
claude_cml_toolkit-2.0.8.dist-info/WHEEL
claude_cml_toolkit-2.0.8.dist-info/entry_points.txt
claude_cml_toolkit-2.0.8.dist-info/top_level.txt
claude_cml_toolkit-2.0.8.dist-info/RECORD
